lx16a/__init__.py
lx16a/console.py
lx16a/constants.py
lx16a/protocol.py
lx16a/servo.py
lx16a-0.0.2.dist-info/WHEEL
lx16a-0.0.2.dist-info/METADATA
lx16a-0.0.2.dist-info/RECORD
