Metadata-Version: 2.1
Name: lx16a
Version: 0.0.2
Summary: Python library to control the Hiwonder LX-16a digital serial servo motor.
Home-page: https://winderresearch.com
License: MIT
Keywords: servo,hiwonder,robotics,lx-16a
Author: Phil Winder
Author-email: phil@WinderResearch.com
Requires-Python: >=3.6,<4
Classifier: License :: OSI Approved :: MIT License
Classifier: Programming Language :: Python :: 3
Classifier: Programming Language :: Python :: 3.6
Classifier: Programming Language :: Python :: 3.7
Classifier: Programming Language :: Python :: 3.8
Requires-Dist: click (>=7.1.2,<8.0.0)
Requires-Dist: construct (>=2.10.56,<3.0.0)
Requires-Dist: loguru (>=0.5.0,<0.6.0)
Requires-Dist: pyserial (>=3.4,<4.0)
Project-URL: Documentation, https://gitlab.com/winderresearch/robotics/lx16a/
Project-URL: Repository, https://gitlab.com/winderresearch/robotics/lx16a/
